welltrajconvert/__init__.py
welltrajconvert/base.py
welltrajconvert/calculable_object.py
welltrajconvert/data_object.py
welltrajconvert/data_source.py
welltrajconvert/deviation_survey.py
welltrajconvert/imports.py
welltrajconvert/utils.py
welltrajconvert/wellbore_trajectory.py
welltrajconvert-0.0.2.dist-info/LICENSE
welltrajconvert-0.0.2.dist-info/METADATA
welltrajconvert-0.0.2.dist-info/WHEEL
welltrajconvert-0.0.2.dist-info/top_level.txt
welltrajconvert-0.0.2.dist-info/RECORD
